wagtailmetadata/__init__.py
wagtailmetadata/jinja2tags.py
wagtailmetadata/models.py
wagtailmetadata/tags.py
wagtailmetadata/utils.py
wagtailmetadata/migrations/0001_initial.py
wagtailmetadata/migrations/0002_auto_20160607_2150.py
wagtailmetadata/migrations/0003_auto_20160909_1000.py
wagtailmetadata/migrations/0004_remove_sitemetadatapreferences.py
wagtailmetadata/migrations/0005_metadatasettings.py
wagtailmetadata/migrations/0006_drop_metadatasettings.py
wagtailmetadata/migrations/__init__.py
wagtailmetadata/templates/wagtailmetadata/parts/tags.html
wagtailmetadata/templatetags/__init__.py
wagtailmetadata/templatetags/wagtailmetadata_tags.py
wagtail_metadata-5.0.0.dist-info/LICENSE
wagtail_metadata-5.0.0.dist-info/METADATA
wagtail_metadata-5.0.0.dist-info/WHEEL
wagtail_metadata-5.0.0.dist-info/top_level.txt
wagtail_metadata-5.0.0.dist-info/RECORD
