Metadata-Version: 2.1
Name: wagtail-metadata
Version: 5.0.0
Summary: A tool to assist with metadata for social media.
Home-page: https://github.com/neon-jungle/wagtail-metadata
Author: Neon Jungle
Author-email: developers@neonjungle.studio
License: BSD License
Classifier: Environment :: Web Environment
Classifier: Intended Audience :: Developers
Classifier: Operating System :: OS Independent
Classifier: Programming Language :: Python
Classifier: Programming Language :: Python :: 3
Classifier: Programming Language :: Python :: 3.8
Classifier: Programming Language :: Python :: 3.9
Classifier: Programming Language :: Python :: 3.10
Classifier: Programming Language :: Python :: 3.11
Classifier: Framework :: Django
Classifier: Framework :: Django :: 3
Classifier: Framework :: Django :: 3.2
Classifier: Framework :: Django :: 4
Classifier: Framework :: Django :: 4.1
Classifier: Framework :: Django :: 4.2
Classifier: Framework :: Wagtail
Classifier: Framework :: Wagtail :: 5
Classifier: License :: OSI Approved :: BSD License
Requires-Python: >=3
License-File: LICENSE
Requires-Dist: wagtail>=5.0
